.DS_Store
graphene_file_upload/__init__.py
graphene_file_upload/scalars.py
graphene_file_upload/utils.py
graphene_file_upload/django/__init__.py
graphene_file_upload/flask/__init__.py
tests/__init__.py
tests/flask_app.py
tests/test_flask.py
tests/test_utils.py
graphene_file_upload-1.2.2.dist-info/LICENSE
graphene_file_upload-1.2.2.dist-info/METADATA
graphene_file_upload-1.2.2.dist-info/WHEEL
graphene_file_upload-1.2.2.dist-info/top_level.txt
graphene_file_upload-1.2.2.dist-info/RECORD
