Metadata-Version: 2.1
Name: graphene_file_upload
Version: 1.2.2
Summary: Lib for adding file upload functionality to GraphQL mutations in Graphene Django and Flask-Graphql
Home-page: https://github.com/lmcgartland/graphene-file-upload
Author: Lucas McGartland
Author-email: lucasmcgartland@gmail.com
License: UNKNOWN
Keywords: graphql,graphene,apollo,upload
Platform: UNKNOWN
Provides-Extra: all
Provides-Extra: django
Provides-Extra: flask
